odoo/addons/product_status/README.rst
odoo/addons/product_status/__init__.py
odoo/addons/product_status/__manifest__.py
odoo/addons/product_status/data/function_deactive_default_product_state_data.xml
odoo/addons/product_status/data/ir_cron.xml
odoo/addons/product_status/data/product_state_data.xml
odoo/addons/product_status/i18n/es.po
odoo/addons/product_status/i18n/it.po
odoo/addons/product_status/i18n/product_status.pot
odoo/addons/product_status/models/__init__.py
odoo/addons/product_status/models/product.py
odoo/addons/product_status/models/product_state.py
odoo/addons/product_status/models/product_template.py
odoo/addons/product_status/readme/CONTRIBUTORS.md
odoo/addons/product_status/readme/CREDITS.md
odoo/addons/product_status/readme/DESCRIPTION.md
odoo/addons/product_status/readme/ROADMAP.md
odoo/addons/product_status/static/description/icon.png
odoo/addons/product_status/static/description/index.html
odoo/addons/product_status/tests/__init__.py
odoo/addons/product_status/tests/test_product_status.py
odoo/addons/product_status/views/product_views.xml
odoo_addon_product_status-18.0.1.0.1.dist-info/METADATA
odoo_addon_product_status-18.0.1.0.1.dist-info/WHEEL
odoo_addon_product_status-18.0.1.0.1.dist-info/top_level.txt
odoo_addon_product_status-18.0.1.0.1.dist-info/RECORD
