Metadata-Version: 2.1
Name: odoo-addon-product_status
Version: 18.0.1.0.1
Requires-Python: >=3.10
Requires-Dist: odoo-addon-product_state==18.0.*
Requires-Dist: odoo==18.0.*
Summary: Product Status Computed From Fields
Home-page: https://github.com/OCA/product-attribute
License: AGPL-3
Author: Camptocamp, Odoo Community Association (OCA)
Author-email: support@odoo-community.org
Classifier: Programming Language :: Python
Classifier: Framework :: Odoo
Classifier: Framework :: Odoo :: 18.0
Classifier: License :: OSI Approved :: GNU Affero General Public License v3
